Workbook
Name Acc.Amt.: Comparison!$E$6
Name Asset.Class: Comparison!$E$9
Name ERR: Comparison!$E$7
Name Investment_Period: Comparison!$H$10
Name IP: Comparison!$E$8
Name MOI: Comparison!$E$10
Name Nature: Comparison!$E$5
Name Return: [1]Calculations!$H$12
Name Savings: Comparison!$E$11

Sheet Dashboard
A1: {=SUM(IF(ISERROR(A3:B7),1,0))} -> 0
L28: ='Audit Report'!D12 -> 0
F35: Investment | G35: Investor Type | H35: Asset Class | K35: Investment | L35: Rate | M35: Tenure | N35: Savings/ROI
G36: Aggressive | H36: =Calculations!D10 -> Real Estate | K36: =Calculations!D8 -> 200000 | L36: =Calculations!D12 -> 0.09 | M36: =Calculations!D9 -> 10 | N36: =Savings -> 28590.842
G37: Conservative | H37: =Calculations!N10 -> Mutual Funds | K37: =Calculations!N8 -> 200000 | L37: =Calculations!D16 -> 0.08 | M37: =Calculations!N9 -> 10 | N37: =Comparison!J11 -> 13805.898

Sheet Calculations
E2: CALCULATIONS
C6: INPUT | M6: INPUT
C7: Nature of Investor | D7: Conservative | H7: Annually | I7: 1 | J7: 12 | M7: Nature of Investor | N7: Conservative
C8: PV | D8: 200000 | H8: Semi Annually | I8: 2 | J8: 6 | M8: FV | N8: 200000
C9: Tenure | D9: 10 | H9: Quaterly | I9: 4 | J9: 3 | M9: Tenure | N9: 10
C10: Asset Class (A) | D10: Real Estate | H10: Monthly | I10: 12 | J10: 1 | M10: Asset Class | N10: Mutual Funds
C11: Frequency | D11: Annually | E11: =VLOOKUP(D11,$H$7:$J$10,2,0) -> 1 | F11: =VLOOKUP(E11,$I$7:$J$10,2,0) -> 12 | M11: Frequency | N11: Annually | O11: =VLOOKUP(N11,$H$7:$J$10,2,0) -> 1 | P11: =VLOOKUP(O11,$I$7:$J$10,2,0) -> 12
C12: Rate | D12: =VLOOKUP(D10,H16:I18,2,0) -> 0.09 | H12: Arrear | I12: 0
C13: Advance | D13: =VLOOKUP(C13,H12:I13,2,0) -> 1 | H13: Advance | I13: 1 | M13: Arrear | N13: =VLOOKUP(M13,H12:I13,2,0) -> 0
C14: Mode of Investment | D14: Annuity | M14: Mode of Investment | N14: Annuity
C15: Asset Class (C) | D15: Mutual Funds
C16: Rate | D16: =VLOOKUP(D15,M16:N18,2,0) -> 0.08 | H16: Equity | I16: 0.1 | M16: Govt. Bonds | N16: 0.0676
H17: Real Estate | I17: 0.09 | M17: FD | N17: 0.065
H18: Gold | I18: 0.28 | M18: Mutual Funds | N18: 0.08
H19: Govt. Bonds | I19: 0.0676
H20: FD | I20: 0.065 | T20: 1
H21: Mutual Funds | I21: 0.08 | T21: 2
T22: 3
T23: 4

Sheet Comparison
D4: OUTPUT | I4: OUTPUT
D5: Nature of Investor | E5: Aggressive | I5: Nature of Investor | J5: Conservative
D6: =IF(Calculations!$C$8="FV","Accumulated Amt.","Amount Invested") -> Amount Invested | E6: 200000 | I6: =IF(Calculations!$C$8="FV","Accumulated Amt.","Amount Invested") -> Amount Invested | J6: 200000
D7: Rate | E7: 0.1 | I7: Rate | J7: 0.0676
D8: Investment Period | E8: 10 | I8: Investment Period | J8: 10
D9: Asset Class | E9: Equity | I9: Asset Class | J9: Mutual Fund
D10: Mode of Investment | E10: Annuity | I10: Mode of Investment | J10: Annuity
D11: Savings/ROI | E11: =IF(Calculations!C8="FV",IF(Calculations!D14="Annuity",-PMT(Calculations!$D$12/Calculations!$E$11,Calculations!$D$9*Calculations!E11,,Calculations!$D$8,Calculations!D13),-PV(Calculations!$D$12,Calculations!D9,,Calculations!$D$8,Calculations!D13)),IF(Calculations!D14="Annuity",PMT(Calculations!D12/Calculations!E11,Calculations!D9*Calculations!E11,-Calculations!D8,,Calculations!D13),FV(Calculations!D12,Calculations!D9,,-Calculations!D8,Calculations!D13))) -> 28590.842 | I11: Savings/ROI | J11: =IF(Calculations!M8="FV",IF(Calculations!N14="Annuity",-PMT(Calculations!$D$16/Calculations!$O$11,Calculations!$N$9*Calculations!O11,,Calculations!$N$8,Calculations!N13),-PV(Calculations!$D$16,Calculations!N9,,Calculations!$N$8,Calculations!N13)),IF(Calculations!N14="Annuity",FV(Calculations!D16/Calculations!O11,Calculations!N9*Calculations!O11,-Calculations!N8,,Calculations!N13),FV(Calculations!D16,Calculations!N9,,-Calculations!N8,Calculations!N13))) -> 13805.898
D15: =IF(Calculations!D7="Aggressive",Calculations!D10,Calculations!D15) -> Mutual Funds
D16: =VLOOKUP(D15,Calculations!H16:I21,2,0) -> 0.08
D20: =IF(Calculations!C8="FV",IF(Calculations!D14="Annuity",-PMT(Comparison!D16/Calculations!E11,Calculations!D9*Calculations!E11,,Calculations!D8,Calculations!D13),-PV(Comparison!D16,Calculations!D9,,Calculations!D8,Calculations!D13)),IF(Calculations!D14="Annuity",FV(Comparison!D16/Calculations!E11,Calculations!D9*Calculations!E11,-Calculations!D8,,Calculations!D13),FV(Comparison!D16,Calculations!D9,,-Calculations!D8,Calculations!D13))) -> 3129097.5

Sheet Audit Report
C8: Sheets | D8: Error
C9: Dashboard | D9: =SUM(IF(ISERROR(Dashboard!C3:AI49),1,0)) -> 0
C10: Calculation | D10: =SUM(IF(ISERROR(Calculations!B1:Q21),1,0)) -> 0
C11: Comparison | D11: =SUM(IF(ISERROR(Comparison!B1:K16)*1,0)) -> 0
C12: Sum | D12: =SUM(D9:D11) -> 0

Sheet Concept Notes
B3: Annually | C3: 1 | D3: 12 | F3: Aggressive-
B4: Semi Annually | C4: 2 | D4: 6 | F4: Equity | G4: 0.1
B5: Quaterly | C5: 4 | D5: 3 | F5: Real Estate | G5: 0.09
B6: Monthly | C6: 12 | D6: 1 | F6: Gold | G6: 0.28
B8: Arrear | C8: 0 | F8: Conservative-
B9: Advance | C9: 1 | F9: Govt. Bonds | G9: 0.0676
F10: FD | G10: 0.065
F11: Mutual Funds | G11: 0.08
